discord_web/__init__.py
discord_web/abc.py
discord_web/checks.py
discord_web/errors.py
discord_web/oauth2.py
discord_web/utils/__init__.py
discord_web/utils/web.py
discord.web-0.0.2.dist-info/LICENSE
discord.web-0.0.2.dist-info/METADATA
discord.web-0.0.2.dist-info/WHEEL
discord.web-0.0.2.dist-info/top_level.txt
discord.web-0.0.2.dist-info/RECORD
