Metadata-Version: 2.1
Name: discord.web
Version: 0.0.2
Summary: An async wrapper for the Discord Oauth2 API
Home-page: UNKNOWN
Author: quiktea
Author-email: wishymovies@gmail.com
License: UNKNOWN
Project-URL: GitHub, https://github.com/quiktea/discord-web
Keywords: python,discord.py,dashboard,discord,api,discord api,web dashboard,website,web
Platform: UNKNOWN
Classifier: Development Status :: 1 - Planning
Classifier: Intended Audience :: Developers
Classifier: Programming Language :: Python :: 3
Classifier: Operating System :: Unix
Classifier: Operating System :: MacOS :: MacOS X
Classifier: Operating System :: Microsoft :: Windows
Requires-Dist: discord.py
Requires-Dist: aiohttp
